scrapy_selenium_addon/__init__.py
scrapy_selenium_addon/http.py
scrapy_selenium_addon/middlewares.py
tests/__init__.py
tests/test_cases.py
tests/test_middlewares.py
scrapy_selenium_addon-0.0.10.dist-info/LICENCE
scrapy_selenium_addon-0.0.10.dist-info/METADATA
scrapy_selenium_addon-0.0.10.dist-info/WHEEL
scrapy_selenium_addon-0.0.10.dist-info/top_level.txt
scrapy_selenium_addon-0.0.10.dist-info/RECORD
