Metadata-Version: 2.1
Name: scrapy-selenium-addon
Version: 0.0.10
Summary: Scrapy with selenium
Home-page: https://github.com/sakarimov/scrapy-selenium-addon
License-File: LICENCE
Requires-Dist: scrapy >=1.0.0
Requires-Dist: selenium >=3.9.0
